scadview/__init__.py
scadview/__main__.py
scadview/app.py
scadview/controller.py
scadview/fonts.py
scadview/load_status.py
scadview/logging_main.py
scadview/logging_worker.py
scadview/mesh_loader_process.py
scadview/module_loader.py
scadview/observable.py
scadview/api/__init__.py
scadview/api/colors.py
scadview/api/linear_extrude.py
scadview/api/surface.py
scadview/api/text_builder.py
scadview/api/utils.py
scadview/render/camera.py
scadview/render/gl_widget_adapter.py
scadview/render/label_atlas.py
scadview/render/label_metrics.py
scadview/render/label_renderee.py
scadview/render/renderee.py
scadview/render/renderer.py
scadview/render/shader_program.py
scadview/render/span.py
scadview/render/trimesh_renderee.py
scadview/resources/DejaVuSansMono.ttf
scadview/resources/meshsee.ico
scadview/resources/splash.png
scadview/resources/xyz_cube.py
scadview/resources/shaders/gnomon_fragment.glsl
scadview/resources/shaders/gnomon_vertex.glsl
scadview/resources/shaders/label_fragment.glsl
scadview/resources/shaders/label_vertex.glsl
scadview/resources/shaders/main_fragment.glsl
scadview/resources/shaders/main_vertex.glsl
scadview/ui/splash.py
scadview/ui/splash_window.py
scadview/ui/wx/action.py
scadview/ui/wx/font_dialog.py
scadview/ui/wx/gl_ui.py
scadview/ui/wx/gl_widget.py
scadview/ui/wx/main_frame.py
scadview-0.2.2.dist-info/METADATA
scadview-0.2.2.dist-info/WHEEL
scadview-0.2.2.dist-info/entry_points.txt
scadview-0.2.2.dist-info/licenses/LICENSE
scadview-0.2.2.dist-info/RECORD
