Metadata-Version: 2.4
Name: scadview
Version: 0.2.2
Summary: A viewer for 3D meshes and constructive solid geometry (CSG) models.
Author-email: Neil Lamoureux <neil.lamoureux@gmail.com>
License-File: LICENSE
Requires-Python: >=3.11
Requires-Dist: manifold3d==3.*
Requires-Dist: matplotlib>=3.10.3
Requires-Dist: moderngl>=5.12.0
Requires-Dist: numpy==2.*
Requires-Dist: pillow>=11.2.1
Requires-Dist: pyobjc-framework-cocoa; platform_system == 'Darwin'
Requires-Dist: pyrr>=0.10.3
Requires-Dist: scipy>=1.16.1
Requires-Dist: shapely>=2.1.1
Requires-Dist: trimesh>=4.6.1
Requires-Dist: wxpython>=4.2.4
